bppibridge.py
bppibridgesq.py
bppibridge/__init__.py
config/__init__.py
config/appConfig.py
config/cmdLineConfig.py
pipelines/__init__.py
pipelines/pipeline.py
pipelines/pipelineFactory.py
pipelines/bppi/__init__.py
pipelines/bppi/bppiPipeline.py
pipelines/bppi/uploadConfig.py
pipelines/bppi/project/__init__.py
pipelines/bppi/project/bppiApiProjectWrapper.py
pipelines/bppi/project/bppiProject.py
pipelines/bppi/repository/__init__.py
pipelines/bppi/repository/bppiApiRepositoryWrapper.py
pipelines/bppi/repository/bppiRepository.py
pipelines/bppi/repository/repConfig.py
pipelines/buslogs/blueprismLogs.py
pipelines/project/__init__.py
pipelines/readers/Reader.py
pipelines/readers/__init__.py
pipelines/readers/bpAPIReader.py
pipelines/readers/csvFileReader.py
pipelines/readers/excelFileReader.py
pipelines/readers/odbcReader.py
pipelines/readers/sapRFCTableReader.py
pipelines/readers/xesFileReader.py
pipelines/readers/builders/SQLBuilder.py
pipelines/readers/builders/__init__.py
pipelines/readers/builders/blueprismSQLBuilder.py
pipelines/repository/__init__.py
pipelines/repository/bppiPLRBluePrismApi.py
pipelines/repository/bppiPLRBluePrismRepo.py
pipelines/repository/bppiPLRCSVFile.py
pipelines/repository/bppiPLRChorusExtract.py
pipelines/repository/bppiPLRExcelFile.py
pipelines/repository/bppiPLRODBC.py
pipelines/repository/bppiPLRSAPRfcTable.py
pipelines/repository/bppiPLRXESFile.py
utils/__init__.py
utils/constants.py
utils/log.py
pyBPPIBridge-0.5.1.dist-info/LICENSE
pyBPPIBridge-0.5.1.dist-info/METADATA
pyBPPIBridge-0.5.1.dist-info/WHEEL
pyBPPIBridge-0.5.1.dist-info/entry_points.txt
pyBPPIBridge-0.5.1.dist-info/top_level.txt
pyBPPIBridge-0.5.1.dist-info/RECORD
