Metadata-Version: 2.1
Name: pyBPPIBridge
Version: 0.5.1
Summary: This solution builds a bridge between Blue Prism Process Intelligence (alias BPPI) and some external data sources (like files, databases via ODBC, SAP and Blue Prism).
Author-email: Benoit Cayla <benoit@exypro.org>
License: MIT License
Project-URL: Bug Tracker, https://exypro.org/Discussions/forum/pybppibridge-solution/
Project-URL: Homepage, https://exypro.org/docs/pybppibridge-documentation/
Classifier: Development Status :: 4 - Beta
Classifier: Operating System :: OS Independent
Classifier: Environment :: Console
Classifier: Programming Language :: Python :: 3.10
Requires-Python: >=3.10
License-File: LICENSE
Requires-Dist: pandas (==2.0.3)
Requires-Dist: openpyxl (==3.1.2)
Requires-Dist: pyodbc (==4.0.39)
Requires-Dist: pyrfc (==3.1)
Requires-Dist: requests (==2.31.0)
Requires-Dist: xmltodict (==0.13.0)
